geopackage_tools/__init__.py
geopackage_tools/app.py
geopackage_tools/config.py
geopackage_tools/main.py
geopackage_tools/infra/__init__.py
geopackage_tools/infra/db_conn.py
geopackage_tools/tests/__init__.py
geopackage_tools/tests/sanbox.py
geopackage_tools/validators/__init__.py
geopackage_tools/validators/validator.py
gpval-0.0.10.dist-info/METADATA
gpval-0.0.10.dist-info/WHEEL
gpval-0.0.10.dist-info/top_level.txt
gpval-0.0.10.dist-info/RECORD
