Metadata-Version: 2.1
Name: gpval
Version: 0.0.10
Summary: geopackages validator utility
Home-page: https://github.com/MapColonies/geopackage_validator.git
Author: MC
License: UNKNOWN
Platform: UNKNOWN
Classifier: Programming Language :: Python :: 3
Classifier: License :: OSI Approved :: MIT License
Classifier: Operating System :: OS Independent
Requires-Python: >=3.6
Requires-Dist: setuptools-scm
Requires-Dist: wheel
